{
  "version": "5",
  "dialect": "pg",
  "entries": [
    {
      "idx": 0,
      "version": "5",
      "when": 1708136658318,
      "tag": "0000_busy_argent",
      "breakpoints": true
    },
    {
      "idx": 1,
      "version": "5",
      "when": 1708277886321,
      "tag": "0001_deep_stick",
      "breakpoints": true
    },
    {
      "idx": 2,
      "version": "5",
      "when": 1708737434311,
      "tag": "0002_powerful_stingray",
      "breakpoints": true
    },
    {
      "idx": 3,
      "version": "5",
      "when": 1708927053410,
      "tag": "0003_eager_master_chief",
      "breakpoints": true
    },
    {
      "idx": 4,
      "version": "5",
      "when": 1708969441658,
      "tag": "0004_sweet_nico_minoru",
      "breakpoints": true
    },
    {
      "idx": 5,
      "version": "5",
      "when": 1709320257401,
      "tag": "0005_milky_kulan_gath",
      "breakpoints": true
    },
    {
      "idx": 6,
      "version": "5",
      "when": 1709320831420,
      "tag": "0006_huge_cerebro",
      "breakpoints": true
    },
    {
      "idx": 7,
      "version": "5",
      "when": 1709760731929,
      "tag": "0007_amused_rogue",
      "breakpoints": true
    },
    {
      "idx": 8,
      "version": "5",
      "when": 1710526849981,
      "tag": "0008_damp_black_crow",
      "breakpoints": true
    },
    {
      "idx": 9,
      "version": "5",
      "when": 1710612948615,
      "tag": "0009_supreme_stone_men",
      "breakpoints": true
    },
    {
      "idx": 10,
      "version": "5",
      "when": 1710616033254,
      "tag": "0010_jazzy_inhumans",
      "breakpoints": true
    },
    {
      "idx": 11,
      "version": "5",
      "when": 1710889382647,
      "tag": "0011_smart_red_wolf",
      "breakpoints": true
    },
    {
      "idx": 12,
      "version": "5",
      "when": 1710891168882,
      "tag": "0012_square_the_watchers",
      "breakpoints": true
    },
    {
      "idx": 13,
      "version": "5",
      "when": 1711083658294,
      "tag": "0013_empty_chimera",
      "breakpoints": true
    },
    {
      "idx": 14,
      "version": "5",
      "when": 1711302688657,
      "tag": "0014_funny_magneto",
      "breakpoints": true
    },
    {
      "idx": 15,
      "version": "5",
      "when": 1711319123008,
      "tag": "0015_stiff_leo",
      "breakpoints": true
    }
  ]
}